LICENSE
README.md
eksupgrade/__init__.py
eksupgrade/__main__.py
eksupgrade/cli.py
eksupgrade/exceptions.py
eksupgrade/models/__init__.py
eksupgrade/models/base.py
eksupgrade/models/eks.py
eksupgrade/src/S3Files/coredns.json
eksupgrade/src/S3Files/kube-proxy-configmap.json
eksupgrade/src/S3Files/kube-proxy.json
eksupgrade/src/S3Files/version_dict.json
eksupgrade/src/S3Files/vpc-cni.json
eksupgrade/src/__init__.py
eksupgrade/src/boto_aws.py
eksupgrade/src/eks_get_image_type.py
eksupgrade/src/k8s_client.py
eksupgrade/src/latest_ami.py
eksupgrade/src/self_managed.py
eksupgrade/starter.py
eksupgrade/utils.py
eksupgrade-0.9.0.dist-info/LICENSE
eksupgrade-0.9.0.dist-info/METADATA
eksupgrade-0.9.0.dist-info/WHEEL
eksupgrade-0.9.0.dist-info/entry_points.txt
eksupgrade-0.9.0.dist-info/RECORD
