Metadata-Version: 2.1
Name: eksupgrade
Version: 0.9.0
Summary: The Amazon EKS cluster upgrade utility
License: MIT-0
Keywords: amazon,aws,aws-samples,eks,kubernetes,upgrade,eksupgrade
Author: EKS Upgrade Maintainers
Author-email: eks-upgrade-maintainers@amazon.com
Requires-Python: >=3.8,<4.0
Classifier: License :: OSI Approved :: MIT No Attribution License (MIT-0)
Classifier: License :: Other/Proprietary License
Classifier: Programming Language :: Python
Classifier: Programming Language :: Python :: 3
Classifier: Programming Language :: Python :: 3.8
Classifier: Programming Language :: Python :: 3.9
Classifier: Programming Language :: Python :: 3.10
Classifier: Programming Language :: Python :: 3.11
Classifier: Programming Language :: Python :: 3
Classifier: Programming Language :: Python :: 3.10
Classifier: Programming Language :: Python :: 3.11
Classifier: Programming Language :: Python :: 3.8
Classifier: Programming Language :: Python :: 3.9
Requires-Dist: boto3 (>=1.26.94,<2.0.0)
Requires-Dist: kubernetes (>=21.0.0,<25.0.0)
Requires-Dist: packaging (>=21.0,<22.0)
Requires-Dist: typer[all] (>=0.7.0,<0.8.0)
